nyaapy/__init__.py
nyaapy/anime_site.py
nyaapy/magnet.py
nyaapy/nyaasi/__init__.py
nyaapy/nyaasi/nyaa.py
nyaapy/nyaasi/sukebei.py
nyaapy/parser.py
nyaapy/torrent.py
nyaapy-0.7.dist-info/LICENSE.md
nyaapy-0.7.dist-info/METADATA
nyaapy-0.7.dist-info/WHEEL
nyaapy-0.7.dist-info/RECORD
