Metadata-Version: 2.1
Name: nyaapy
Version: 0.7
Summary: Unofficial Python wrapper for NyaaPantsu API and Nyaa.si
License: MIT
Author: Juanjo Salvador
Author-email: juanjosalvador@netc.eu
Requires-Python: >=3.10,<4.0
Classifier: License :: OSI Approved :: MIT License
Classifier: Programming Language :: Python :: 3
Classifier: Programming Language :: Python :: 3.10
Classifier: Programming Language :: Python :: 3.11
Classifier: Programming Language :: Python :: 3.12
Requires-Dist: lxml (>=5.2.2,<6.0.0)
Requires-Dist: requests (>=2.32.3,<3.0.0)
